<?xml version = '1.0' encoding = 'UTF-8'?>
<Diagram class="oracle.dbtools.crest.swingui.relational.DPVRelational" name="Relational_7" id="C4F21AEB-F17B-19D7-5973-68715E172B5D">
<createdBy>steffanny</createdBy>
<modifiedBy>steffanny</modifiedBy>
<createdTime>2023-05-14 20:12:36 UTC</createdTime>
<autoRoute>false</autoRoute>
<boxInbox>true</boxInbox>
<showLegend>false</showLegend>
<showLabels>false</showLabels>
<showRelAttributes>false</showRelAttributes>
<gridEnabled>false</gridEnabled>
<showGrid>false</showGrid>
<diagramColor>-1</diagramColor>
<display>false</display>
<notation>1</notation>
<objectViews>
<OView class="oracle.dbtools.crest.swingui.relational.TVTable" oid="052F328E-EBB1-C488-954C-1A0D3E88E724" otype="Table" vid="A9C69450-B138-FA7F-0B0C-C293E67AEB2C">
<hideElementsInCurrentOnly>false</hideElementsInCurrentOnly>
<bounds x="809" y="1055" width="260" height="136"/>
</OView>
<OView class="oracle.dbtools.crest.swingui.relational.TVTable" oid="114174C2-0B45-E6B9-5B7B-313080BA0C94" otype="Table" vid="DF808697-4F0B-A2DD-05FF-69CF60AD8879">
<hideElementsInCurrentOnly>false</hideElementsInCurrentOnly>
<bounds x="1297" y="266" width="292" height="218"/>
</OView>
<OView class="oracle.dbtools.crest.swingui.relational.TVTable" oid="1927668D-94F5-2607-6391-C397D1B14ADB" otype="Table" vid="8E9D0C06-E2A8-AFD1-200A-386445E3D87B">
<hideElementsInCurrentOnly>false</hideElementsInCurrentOnly>
<bounds x="55" y="1140" width="242" height="168"/>
</OView>
<OView class="oracle.dbtools.crest.swingui.relational.TVTable" oid="36A294B4-8787-7271-2A43-59AED90D6EED" otype="Table" vid="D3D077D6-B44E-6586-7C22-8A490E7E1055">
<hideElementsInCurrentOnly>false</hideElementsInCurrentOnly>
<bounds x="369" y="4" width="304" height="219"/>
</OView>
<OView class="oracle.dbtools.crest.swingui.relational.TVTable" oid="386C4A3C-D986-C6DB-CF69-221ACC81C715" otype="Table" vid="4D35DCCC-F064-CC79-FDAA-847CDA6C2643">
<hideElementsInCurrentOnly>false</hideElementsInCurrentOnly>
<bounds x="813" y="622" width="229" height="94"/>
</OView>
<OView class="oracle.dbtools.crest.swingui.relational.TVTable" oid="57D65545-9FD4-AA1B-CEB4-8EA9E039D52E" otype="Table" vid="B08BF9DA-6AEB-C86C-0834-05FF78787C35">
<hideElementsInCurrentOnly>false</hideElementsInCurrentOnly>
<bounds x="314" y="1405" width="396" height="150"/>
</OView>
<OView class="oracle.dbtools.crest.swingui.relational.TVTable" oid="5EA90534-8353-B9CB-D162-C6A0D271FE78" otype="Table" vid="7BF8BA83-C076-923E-DA74-B857964F1C11">
<hideElementsInCurrentOnly>false</hideElementsInCurrentOnly>
<bounds x="397" y="320" width="239" height="100"/>
</OView>
<OView class="oracle.dbtools.crest.swingui.relational.TVTable" oid="628BD940-34BA-A48D-2F8B-E4F1E56A6BBF" otype="Table" vid="13496F59-4281-0BA2-A458-37B12D240BBA">
<hideElementsInCurrentOnly>false</hideElementsInCurrentOnly>
<bounds x="377" y="1117" width="265" height="201"/>
</OView>
<OView class="oracle.dbtools.crest.swingui.relational.TVTable" oid="8B060289-B8AC-1D95-92E4-0B7A4492C5D4" otype="Table" vid="CF66FD9D-FC10-5ADE-A79B-49015EDCA963">
<hideElementsInCurrentOnly>false</hideElementsInCurrentOnly>
<bounds x="17" y="855" width="290" height="160"/>
</OView>
<OView class="oracle.dbtools.crest.swingui.relational.TVTable" oid="928A90B4-CC41-EFD7-16C0-1E28154E294B" otype="Table" vid="5B49CD11-3CE2-3969-8507-E90A49B373B4">
<hideElementsInCurrentOnly>false</hideElementsInCurrentOnly>
<bounds x="1325" y="1064" width="241" height="126"/>
</OView>
<OView class="oracle.dbtools.crest.swingui.relational.TVTable" oid="933D1912-DFCF-CC1B-C34A-E02B72C445E1" otype="Table" vid="09E7D016-CBCA-53B2-8881-DF906B31FCFE">
<hideElementsInCurrentOnly>false</hideElementsInCurrentOnly>
<bounds x="50" y="164" width="185" height="94"/>
</OView>
<OView class="oracle.dbtools.crest.swingui.relational.TVTable" oid="B873C0F8-E033-9854-FC3A-8534D86D30AB" otype="Table" vid="D8753FA6-0ACF-09D8-F014-B1C9880C9669">
<hideElementsInCurrentOnly>false</hideElementsInCurrentOnly>
<bounds x="351" y="834" width="325" height="210"/>
</OView>
<OView class="oracle.dbtools.crest.swingui.relational.TVTable" oid="B93B2149-45F9-173B-240D-BBB408BBA567" otype="Table" vid="05511BF8-625F-E987-EC44-E154972C3A1E">
<hideElementsInCurrentOnly>false</hideElementsInCurrentOnly>
<bounds x="375" y="524" width="286" height="252"/>
</OView>
<OView class="oracle.dbtools.crest.swingui.relational.TVTable" oid="D5B51AFF-9484-3A2D-3F6F-3C43167AEFDB" otype="Table" vid="B7B13FE9-AAD1-3580-2814-41AF17BFBFEA">
<hideElementsInCurrentOnly>false</hideElementsInCurrentOnly>
<bounds x="19" y="312" width="250" height="110"/>
</OView>
<OView class="oracle.dbtools.crest.swingui.relational.TVTable" oid="E750E46D-5646-30E0-5590-71EBCF19ECB0" otype="Table" vid="155668EF-2D5C-3169-8581-1555CC2E32AC">
<hideElementsInCurrentOnly>false</hideElementsInCurrentOnly>
<bounds x="1074" y="500" width="309" height="220"/>
</OView>
<OView class="oracle.dbtools.crest.swingui.relational.TVTable" oid="F892988D-018D-38D4-8A24-18E46D203915" otype="Table" vid="C8B07D64-6F8B-5029-8000-5D48C12858A4">
<hideElementsInCurrentOnly>false</hideElementsInCurrentOnly>
<bounds x="1117" y="1424" width="267" height="136"/>
</OView>
</objectViews>
<connectors>
<Connector class="oracle.dbtools.crest.swingui.relational.TVFKRelation" oid="0E47F9D6-D078-3E81-D996-99EDA4064F85" otype="FKIndexAssociation" vid_source="B08BF9DA-6AEB-C86C-0834-05FF78787C35" vid_target="13496F59-4281-0BA2-A458-37B12D240BBA">
<hideElementsInCurrentOnly>false</hideElementsInCurrentOnly>
<backgroundColor>-16777216</backgroundColor>
<lineWidth>1</lineWidth>
<points>
<point x="509" y="1405"/>
<point x="509" y="1318"/>
</points>
</Connector>
<Connector class="oracle.dbtools.crest.swingui.relational.TVFKRelation" oid="3C8F4BEE-165E-C77A-CDA4-7D87C5D60F24" otype="FKIndexAssociation" vid_source="4D35DCCC-F064-CC79-FDAA-847CDA6C2643" vid_target="05511BF8-625F-E987-EC44-E154972C3A1E">
<hideElementsInCurrentOnly>false</hideElementsInCurrentOnly>
<backgroundColor>-16777216</backgroundColor>
<lineWidth>1</lineWidth>
<points>
<point x="813" y="669"/>
<point x="661" y="669"/>
</points>
</Connector>
<Connector class="oracle.dbtools.crest.swingui.relational.TVFKRelation" oid="3CECD0A5-46C3-139C-0CE7-CFB1A283A531" otype="FKIndexAssociation" vid_source="7BF8BA83-C076-923E-DA74-B857964F1C11" vid_target="05511BF8-625F-E987-EC44-E154972C3A1E">
<hideElementsInCurrentOnly>false</hideElementsInCurrentOnly>
<backgroundColor>-16777216</backgroundColor>
<lineWidth>1</lineWidth>
<points>
<point x="516" y="420"/>
<point x="516" y="524"/>
</points>
</Connector>
<Connector class="oracle.dbtools.crest.swingui.relational.TVFKRelation" oid="483F4606-AD11-0728-233C-1716FEF485A7" otype="FKIndexAssociation" vid_source="13496F59-4281-0BA2-A458-37B12D240BBA" vid_target="D8753FA6-0ACF-09D8-F014-B1C9880C9669">
<hideElementsInCurrentOnly>false</hideElementsInCurrentOnly>
<backgroundColor>-16777216</backgroundColor>
<lineWidth>1</lineWidth>
<points>
<point x="509" y="1117"/>
<point x="509" y="1044"/>
</points>
</Connector>
<Connector class="oracle.dbtools.crest.swingui.relational.TVFKRelation" oid="57C2984E-AC45-2C96-6E0C-A5CDAC20BF3C" otype="FKIndexAssociation" vid_source="05511BF8-625F-E987-EC44-E154972C3A1E" vid_target="D8753FA6-0ACF-09D8-F014-B1C9880C9669">
<hideElementsInCurrentOnly>false</hideElementsInCurrentOnly>
<backgroundColor>-16777216</backgroundColor>
<lineWidth>1</lineWidth>
<points>
<point x="518" y="776"/>
<point x="518" y="834"/>
</points>
</Connector>
<Connector class="oracle.dbtools.crest.swingui.relational.TVFKRelation" oid="6A3AEA52-759C-4B69-67B3-4CCF9D32ED32" otype="FKIndexAssociation" vid_source="7BF8BA83-C076-923E-DA74-B857964F1C11" vid_target="DF808697-4F0B-A2DD-05FF-69CF60AD8879">
<hideElementsInCurrentOnly>false</hideElementsInCurrentOnly>
<backgroundColor>-16777216</backgroundColor>
<lineWidth>1</lineWidth>
<points>
<point x="636" y="370"/>
<point x="1297" y="370"/>
</points>
</Connector>
<Connector class="oracle.dbtools.crest.swingui.relational.TVFKRelation" oid="873586A1-F366-16BB-5EF4-E137A7581CBB" otype="FKIndexAssociation" vid_source="05511BF8-625F-E987-EC44-E154972C3A1E" vid_target="155668EF-2D5C-3169-8581-1555CC2E32AC">
<hideElementsInCurrentOnly>false</hideElementsInCurrentOnly>
<backgroundColor>-16777216</backgroundColor>
<lineWidth>1</lineWidth>
<points>
<point x="661" y="622"/>
<point x="1074" y="622"/>
</points>
</Connector>
<Connector class="oracle.dbtools.crest.swingui.relational.TVFKRelation" oid="963A3C87-C89A-F4B2-731D-6D33B2886A4E" otype="FKIndexAssociation" vid_source="13496F59-4281-0BA2-A458-37B12D240BBA" vid_target="8E9D0C06-E2A8-AFD1-200A-386445E3D87B">
<hideElementsInCurrentOnly>false</hideElementsInCurrentOnly>
<backgroundColor>-16777216</backgroundColor>
<lineWidth>1</lineWidth>
<points>
<point x="377" y="1224"/>
<point x="297" y="1224"/>
</points>
</Connector>
<Connector class="oracle.dbtools.crest.swingui.relational.TVFKRelation" oid="A2F63447-BA8C-AE4F-1CAD-9A8749E273DA" otype="FKIndexAssociation" vid_source="4D35DCCC-F064-CC79-FDAA-847CDA6C2643" vid_target="A9C69450-B138-FA7F-0B0C-C293E67AEB2C">
<hideElementsInCurrentOnly>false</hideElementsInCurrentOnly>
<backgroundColor>-16777216</backgroundColor>
<lineWidth>1</lineWidth>
<points>
<point x="927" y="716"/>
<point x="927" y="1055"/>
</points>
</Connector>
<Connector class="oracle.dbtools.crest.swingui.relational.TVFKRelation" oid="AF7ECA32-D3CD-4614-9FAB-EB4C3E28AEF3" otype="FKIndexAssociation" vid_source="DF808697-4F0B-A2DD-05FF-69CF60AD8879" vid_target="5B49CD11-3CE2-3969-8507-E90A49B373B4">
<hideElementsInCurrentOnly>false</hideElementsInCurrentOnly>
<backgroundColor>-16777216</backgroundColor>
<lineWidth>1</lineWidth>
<points>
<point x="1445" y="484"/>
<point x="1445" y="1064"/>
</points>
</Connector>
<Connector class="oracle.dbtools.crest.swingui.relational.TVFKRelation" oid="BDC8FCB9-71C5-01C6-523A-32C748DA8C4D" otype="FKIndexAssociation" vid_source="5B49CD11-3CE2-3969-8507-E90A49B373B4" vid_target="A9C69450-B138-FA7F-0B0C-C293E67AEB2C">
<hideElementsInCurrentOnly>false</hideElementsInCurrentOnly>
<backgroundColor>-16777216</backgroundColor>
<lineWidth>1</lineWidth>
<points>
<point x="1325" y="1127"/>
<point x="1069" y="1127"/>
</points>
</Connector>
<Connector class="oracle.dbtools.crest.swingui.relational.TVFKRelation" oid="C4A4DB02-96C0-BDC7-A345-5CB06F825204" otype="FKIndexAssociation" vid_source="C8B07D64-6F8B-5029-8000-5D48C12858A4" vid_target="B08BF9DA-6AEB-C86C-0834-05FF78787C35">
<hideElementsInCurrentOnly>false</hideElementsInCurrentOnly>
<backgroundColor>-16777216</backgroundColor>
<lineWidth>1</lineWidth>
<points>
<point x="1117" y="1489"/>
<point x="710" y="1489"/>
</points>
</Connector>
<Connector class="oracle.dbtools.crest.swingui.relational.TVFKRelation" oid="C4F88345-5B1F-199C-8989-D7484EB32A1C" otype="FKIndexAssociation" vid_source="A9C69450-B138-FA7F-0B0C-C293E67AEB2C" vid_target="155668EF-2D5C-3169-8581-1555CC2E32AC">
<hideElementsInCurrentOnly>false</hideElementsInCurrentOnly>
<backgroundColor>-16777216</backgroundColor>
<lineWidth>1</lineWidth>
<points>
<point x="977" y="1055"/>
<point x="1166" y="720"/>
</points>
</Connector>
<Connector class="oracle.dbtools.crest.swingui.relational.TVFKRelation" oid="C801F96A-F153-D537-CC74-FAB5EAFA804C" otype="FKIndexAssociation" vid_source="7BF8BA83-C076-923E-DA74-B857964F1C11" vid_target="B7B13FE9-AAD1-3580-2814-41AF17BFBFEA">
<hideElementsInCurrentOnly>false</hideElementsInCurrentOnly>
<backgroundColor>-16777216</backgroundColor>
<lineWidth>1</lineWidth>
<points>
<point x="397" y="370"/>
<point x="269" y="370"/>
</points>
</Connector>
<Connector class="oracle.dbtools.crest.swingui.relational.TVFKRelation" oid="CD02514E-BD79-8568-3DF1-4B34A4A9FB96" otype="FKIndexAssociation" vid_source="C8B07D64-6F8B-5029-8000-5D48C12858A4" vid_target="155668EF-2D5C-3169-8581-1555CC2E32AC">
<hideElementsInCurrentOnly>false</hideElementsInCurrentOnly>
<backgroundColor>-16777216</backgroundColor>
<lineWidth>1</lineWidth>
<points>
<point x="1250" y="1424"/>
<point x="1250" y="720"/>
</points>
</Connector>
<Connector class="oracle.dbtools.crest.swingui.relational.TVFKRelation" oid="CDA0D2C6-0C0A-AEE2-6BD4-8D746F713B7B" otype="FKIndexAssociation" vid_source="A9C69450-B138-FA7F-0B0C-C293E67AEB2C" vid_target="B08BF9DA-6AEB-C86C-0834-05FF78787C35">
<hideElementsInCurrentOnly>false</hideElementsInCurrentOnly>
<backgroundColor>-16777216</backgroundColor>
<lineWidth>1</lineWidth>
<points>
<point x="857" y="1191"/>
<point x="601" y="1405"/>
</points>
</Connector>
<Connector class="oracle.dbtools.crest.swingui.relational.TVFKRelation" oid="CEA7F3EC-1E79-5C47-BE7F-4C0B349431CB" otype="FKIndexAssociation" vid_source="09E7D016-CBCA-53B2-8881-DF906B31FCFE" vid_target="B7B13FE9-AAD1-3580-2814-41AF17BFBFEA">
<hideElementsInCurrentOnly>false</hideElementsInCurrentOnly>
<backgroundColor>-16777216</backgroundColor>
<lineWidth>1</lineWidth>
<points>
<point x="142" y="258"/>
<point x="142" y="312"/>
</points>
</Connector>
<Connector class="oracle.dbtools.crest.swingui.relational.TVFKRelation" oid="CFDDD06B-2852-73D8-7504-38A5307F58EE" otype="FKIndexAssociation" vid_source="7BF8BA83-C076-923E-DA74-B857964F1C11" vid_target="D3D077D6-B44E-6586-7C22-8A490E7E1055">
<hideElementsInCurrentOnly>false</hideElementsInCurrentOnly>
<backgroundColor>-16777216</backgroundColor>
<lineWidth>1</lineWidth>
<points>
<point x="516" y="320"/>
<point x="516" y="223"/>
</points>
</Connector>
<Connector class="oracle.dbtools.crest.swingui.relational.TVFKRelation" oid="F6682984-C03E-2F50-5142-BB951065438E" otype="FKIndexAssociation" vid_source="D8753FA6-0ACF-09D8-F014-B1C9880C9669" vid_target="CF66FD9D-FC10-5ADE-A79B-49015EDCA963">
<hideElementsInCurrentOnly>false</hideElementsInCurrentOnly>
<backgroundColor>-16777216</backgroundColor>
<lineWidth>1</lineWidth>
<points>
<point x="351" y="935"/>
<point x="307" y="935"/>
</points>
</Connector>
</connectors>
</Diagram>
